Metadata-Version: 2.4
Name: perplexity-mcp-fastmcp
Version: 0.1.7
Summary: MCP integration for Perplexity AI web searches
Project-URL: Homepage, https://github.com/fastmcp-me/perplexity-mcp#readme
Project-URL: Repository, https://github.com/fastmcp-me/perplexity-mcp.git
Project-URL: Issues, https://github.com/fastmcp-me/perplexity-mcp/issues
Author: Jason Allen
License-File: LICENSE
Requires-Python: >=3.11
Requires-Dist: aiohttp>=3.8.0
Requires-Dist: mcp>=1.0.2
Requires-Dist: pydantic>=2.0.0
